phonenumbers_jp/__init__.py
phonenumbers_jp/_data.py
phonenumbers_jp/types.py
phonenumbers_jp-0.1.0.dist-info/WHEEL
phonenumbers_jp-0.1.0.dist-info/LICENSE.txt
phonenumbers_jp-0.1.0.dist-info/METADATA
phonenumbers_jp-0.1.0.dist-info/RECORD
