Metadata-Version: 2.1
Name: phonenumbers-jp
Version: 0.1.0
Summary: Analyze Japanese domestic phone numbers
Home-page: https://github.com/ciscorn/phonenumbers-jp-py
License: MIT
Author: Taku Fukada
Author-email: naninunenor@gmail.com
Requires-Python: >=3.7,<4.0
Classifier: License :: OSI Approved :: MIT License
Classifier: Operating System :: OS Independent
Classifier: Programming Language :: Python :: 3
Classifier: Programming Language :: Python :: 3.7
Classifier: Programming Language :: Python :: 3.8
Classifier: Programming Language :: Python :: 3.9
Classifier: Programming Language :: Python :: 3.10
Classifier: Programming Language :: Python :: 3.11
Classifier: Topic :: Software Development :: Libraries :: Python Modules
Project-URL: Repository, https://github.com/ciscorn/phonenumbers-jp-py
